lorempicsum/__init__.py
lorempicsum/__main__.py
lorempicsum/cli.py
lorempicsum/engine.py
lorempicsum-0.0.11.dist-info/LICENSE
lorempicsum-0.0.11.dist-info/METADATA
lorempicsum-0.0.11.dist-info/WHEEL
lorempicsum-0.0.11.dist-info/top_level.txt
lorempicsum-0.0.11.dist-info/RECORD
