Metadata-Version: 2.1
Name: lorempicsum
Version: 0.0.11
Summary: 0-dependency CLI tool for reproducibly downloading random images.
Home-page: https://github.com/Expan75/py-lorem-picsum
Author: Erik Hakansson
License: UNKNOWN
Project-URL: Bug Tracker, https://github.com/Expan75/py-lorem-picsum/issues
Platform: UNKNOWN
Classifier: Programming Language :: Python :: 3
Classifier: License :: OSI Approved :: MIT License
Classifier: Operating System :: OS Independent
Requires-Python: >=3.8
License-File: LICENSE
